femtograd/__init__.py
femtograd/engine.py
femtograd/graph.py
femtograd/nn.py
femtograd/primes.pyx
femtograd/rnn.py
femtograd-0.0.2.dist-info/LICENSE
femtograd-0.0.2.dist-info/METADATA
femtograd-0.0.2.dist-info/WHEEL
femtograd-0.0.2.dist-info/top_level.txt
femtograd-0.0.2.dist-info/RECORD
