Metadata-Version: 2.1
Name: femtograd
Version: 0.0.2
Summary: Mini deep learning framework
Author-email: Marco Salvalaggio <mar.salvalaggio@gmail.com>
License: Copyright (c) 2018 The Python Packaging Authority
Project-URL: Homepage, https://github.com/marcosalvalaggio/femtograd
Project-URL: Bug Tracker, https://github.com/marcosalvalaggio/femtogradissues
Classifier: Programming Language :: Python :: 3
Classifier: License :: OSI Approved :: MIT License
Classifier: Operating System :: OS Independent
Requires-Python: >=3.7
License-File: LICENSE
Requires-Dist: graphviz
